opengit/__init__.py
opengit/main.py
opengit-0.1.0.dist-info/LICENSE
opengit-0.1.0.dist-info/METADATA
opengit-0.1.0.dist-info/WHEEL
opengit-0.1.0.dist-info/entry_points.txt
opengit-0.1.0.dist-info/top_level.txt
opengit-0.1.0.dist-info/RECORD
