Metadata-Version: 2.1
Name: opengit
Version: 0.1.0
Summary: A simple command-line tool to open the remote repository of a local git repository.
Home-page: https://github.com/marwanhawari/opengit
Author: Marwan Hawari
Author-email: marwan.hawari@gmail.com
License: MIT
Platform: UNKNOWN
Classifier: Programming Language :: Python :: 3
Classifier: License :: OSI Approved :: MIT License
Classifier: Operating System :: OS Independent
Requires-Python: >=3.6
License-File: LICENSE
